odoo/addons/base_maintenance_group/README.rst
odoo/addons/base_maintenance_group/__init__.py
odoo/addons/base_maintenance_group/__manifest__.py
odoo/addons/base_maintenance_group/data/maintenance_data.xml
odoo/addons/base_maintenance_group/i18n/base_maintenance_group.pot
odoo/addons/base_maintenance_group/i18n/es.po
odoo/addons/base_maintenance_group/i18n/fr.po
odoo/addons/base_maintenance_group/i18n/it.po
odoo/addons/base_maintenance_group/i18n/pt_BR.po
odoo/addons/base_maintenance_group/i18n/sk.po
odoo/addons/base_maintenance_group/readme/CONTRIBUTORS.md
odoo/addons/base_maintenance_group/readme/DESCRIPTION.md
odoo/addons/base_maintenance_group/readme/USAGE.md
odoo/addons/base_maintenance_group/security/maintenance_security.xml
odoo/addons/base_maintenance_group/static/description/icon.png
odoo/addons/base_maintenance_group/static/description/index.html
odoo/addons/base_maintenance_group/views/maintenance_views.xml
odoo_addon_base_maintenance_group-18.0.1.0.0.4.dist-info/METADATA
odoo_addon_base_maintenance_group-18.0.1.0.0.4.dist-info/WHEEL
odoo_addon_base_maintenance_group-18.0.1.0.0.4.dist-info/top_level.txt
odoo_addon_base_maintenance_group-18.0.1.0.0.4.dist-info/RECORD
